{
    "2": {
        "Country": "United States",
        "State": "New Jersey",
        "City": "",
        "Continent": "North America",
        "Company": "Amazon",
        "Company city": "Seattle",
        "Company state": "Washington",
        "Affected population": [
            "Amazon warehouse workers"
        ],
        "Number of people actually affected": 25,
        "Number of people potentially affected": "Unknown",
        "Classes of irresponsible AI use": [
            "Human Incompetence"
        ],
        "Subclasses": {
            "Human Incompetence": [
                "Technical"
            ]
        },
        "Sub-subclass": [],
        "Area of AI Application": "Warehouse Automation",
        "Online": "No"
    }
}