{
    "76": {
        "Country": "Worldwide",
        "State": "",
        "City": "",
        "Continent": "Worldwide",
        "Company": "Unknown",
        "Company city": "Unknown",
        "Company state": "",
        "Affected population": [
            "Children in Buenos Aires"
        ],
        "Number of people actually affected": "Unknown",
        "Number of people potentially affected": "Unknown",
        "Class of irresponsible AI use": [
            "Discrimination",
            "Human Incompetence"
        ],
        "Subclasses": {
            "Discrimination": [
                "Facial"
            ],
            "Human Incompetence": [
                "Technical"
            ]
        },
        "Sub-subclass": {
            "Facial": []
        },
        "Area of AI Application": "Facial Recognition",
        "Online": "No"
    }
}