{
    "174": {
        "Country": "Worldwide",
        "State": "",
        "City": "",
        "Continent": "Worldwide",
        "Company": "Google LLC",
        "Company city": "Mountain View",
        "Company state": "California",
        "Affected population": [
            "LinkedIn Users"
        ],
        "Number of people actually affected": "Unknown",
        "Number of people potentially affected": "Thousands",
        "Class of irresponsible AI use": [
            "Disinformation",
            "Human Incompetence",
            "Copyright Violation"
        ],
        "Subclasses": {
            "Human Incompetence": [
                "Technical"
            ]
        },
        "Sub-subclass": [],
        "Area of AI Application": "Image Generation",
        "Online": "Yes"
    }
}