{
    "129": {
        "Country": "Worldwide",
        "State": "",
        "City": "",
        "Continent": "Worldwide",
        "Company": "Facebook",
        "Company city": "Menlo Park",
        "Company state": "California",
        "Affected population": [
            "Users of Facebook Platform"
        ],
        "Number of people actually affected": "Unknown",
        "Number of people potentially affected": "Billions",
        "Class of irresponsible AI use": [
            "Human Incompetence",
            "Disinformation"
        ],
        "Subclasses": {
            "Human Incompetence": [
                "Technical"
            ],
            "Disinformation": [
                "Textual",
                "Image",
                "Video",
                "Audio"
            ]
        },
        "Sub-subclass": [],
        "Area of AI Application": "Automated Moderation",
        "Online": "Yes"
    }
}